pyblkid.py
pyblkid-0.1.0.dist-info/WHEEL
pyblkid-0.1.0.dist-info/METADATA
pyblkid-0.1.0.dist-info/RECORD
