Metadata-Version: 2.1
Name: pyblkid
Version: 0.1.0
Summary: 
Author: Jan Willems
Author-email: jw@elevenbts.com
Requires-Python: >=3.8,<4.0
Classifier: Programming Language :: Python :: 3
Classifier: Programming Language :: Python :: 3.8
Requires-Dist: pydantic (>=1.6.1,<2.0.0)
